xmlexicon/__init__.py
xmlexicon/xmlexicon.py
xmlexicon-0.0.1.dist-info/LICENSE
xmlexicon-0.0.1.dist-info/METADATA
xmlexicon-0.0.1.dist-info/WHEEL
xmlexicon-0.0.1.dist-info/top_level.txt
xmlexicon-0.0.1.dist-info/RECORD
