Metadata-Version: 2.1
Name: xmlexicon
Version: 0.0.1
Summary: Package for transforming a .csv file containing a trilingual dictionary into TEI XML. At this moment this package works for that particular .csv file.
Home-page: https://github.com/wildmary/TEI-RDF-encoded-Dictionary
Author: Maria Levchenko
Author-email: wildmary@yandex.ru
Project-URL: Bug Tracker, https://github.com/wildmary/TEI-RDF-encoded-Dictionary/issues
Classifier: Programming Language :: Python :: 3
Classifier: License :: OSI Approved :: MIT License
Classifier: Operating System :: OS Independent
Requires-Python: >=3.0
License-File: LICENSE
